egtaonline/__init__.py
egtaonline/__main__.py
egtaonline/api.py
egtaonline/mockserver.py
egtaonlineapi-0.8.7.dist-info/METADATA
egtaonlineapi-0.8.7.dist-info/RECORD
egtaonlineapi-0.8.7.dist-info/WHEEL
egtaonlineapi-0.8.7.dist-info/entry_points.txt
egtaonlineapi-0.8.7.dist-info/top_level.txt
