Metadata-Version: 2.1
Name: egtaonlineapi
Version: 0.8.7
Summary: Various APIs for egtaonline
Home-page: https://github.com/egtaonline/egtaonline-api.git
Author: Strategic Reasoning Group
Author-email: strategic.reasoning.group@umich.edu
License: Apache 2.0
Platform: UNKNOWN
Provides-Extra: dev
Requires-Dist: inflection (~=0.3)
Requires-Dist: jsonschema (~=2.6)
Requires-Dist: lxml (~=4.2)
Requires-Dist: requests-mock (~=1.4)
Requires-Dist: requests (~=2.18)
Requires-Dist: tabulate (~=0.8)
Provides-Extra: dev
Requires-Dist: ipython (~=6.3); extra == 'dev'
Requires-Dist: pylint-quotes (~=0.1); extra == 'dev'
Requires-Dist: pylint (~=1.8); extra == 'dev'
Requires-Dist: mock (~=2.0); extra == 'dev'
Requires-Dist: pytest-asyncio (~=0.8); extra == 'dev'
Requires-Dist: pytest-cov (~=2.5); extra == 'dev'
Requires-Dist: pytest-env (~=0.6); extra == 'dev'
Requires-Dist: pytest-xdist (~=1.18); extra == 'dev'
Requires-Dist: pytest (~=3.2); extra == 'dev'
Requires-Dist: sphinx (~=1.7); extra == 'dev'
Requires-Dist: twine (~=1.9); extra == 'dev'
Requires-Dist: wheel (~=0.30); extra == 'dev'
